mkapidocs/__init__.py
mkapidocs/builder.py
mkapidocs/cli.py
mkapidocs/console.py
mkapidocs/generator.py
mkapidocs/models.py
mkapidocs/project_detection.py
mkapidocs/validators.py
mkapidocs/version.py
mkapidocs/yaml_utils.py
mkapidocs/resources/__init__.py
mkapidocs/templates/__init__.py
mkapidocs/templates/c_api_md_template.py
mkapidocs/templates/cli_md_template.py
mkapidocs/templates/gitlab-ci.yml
mkapidocs/templates/index_md_template.py
mkapidocs/templates/install_md_template.py
mkapidocs/templates/mkdocs.yml.j2
mkapidocs/templates/pages.yml
mkapidocs/templates/python_api_md_template.py
mkapidocs-0.1.0.dist-info/METADATA
mkapidocs-0.1.0.dist-info/WHEEL
mkapidocs-0.1.0.dist-info/entry_points.txt
mkapidocs-0.1.0.dist-info/licenses/LICENSE
mkapidocs-0.1.0.dist-info/RECORD
