Metadata-Version: 2.4
Name: mkapidocs
Version: 0.1.0
Summary: Automated documentation setup tool for Python projects using MkDocs with GitHub Pages or GitLab Pages. Intelligently detects project features (C/C++ code, Typer CLI, private registries) and generates comprehensive MkDocs documentation with Material theme, API references, CI/CD workflows, and docstring linting configuration.
Author-email: Jamie Nelson <jamie.nelson@assaabloy.com>
License: Unlicense
License-File: LICENSE
Requires-Python: <3.13,>=3.11
Requires-Dist: httpx>=0.28.1
Requires-Dist: jinja2>=3.1.6
Requires-Dist: mkdocs-literate-nav>=0.6.1
Requires-Dist: mkdocs-material>=9.5.0
Requires-Dist: mkdocs-mermaid2-plugin>=1.1.1
Requires-Dist: mkdocs-typer2>=0.1.0
Requires-Dist: mkdocs>=1.6.0
Requires-Dist: mkdocstrings[python]>=0.26.0
Requires-Dist: mkdoxy>=1.2.3
Requires-Dist: pydantic>=2.12.2
Requires-Dist: python-dotenv>=1.1.1
Requires-Dist: ruamel-yaml>=0.18.0
Requires-Dist: termynal>=0.12.1
Requires-Dist: tomlkit>=0.12.0
Requires-Dist: typer>=0.19.2
